pylacrossapi/__init__.py
pylacrossapi-0.3.dist-info/DESCRIPTION.rst
pylacrossapi-0.3.dist-info/METADATA
pylacrossapi-0.3.dist-info/RECORD
pylacrossapi-0.3.dist-info/WHEEL
pylacrossapi-0.3.dist-info/metadata.json
pylacrossapi-0.3.dist-info/top_level.txt
