Metadata-Version: 2.0
Name: pylacrossapi
Version: 0.3
Summary: Access your Lacrosse Temperature Device
Home-page: http://github.com/concongo/pylacrossapi
Author: J. Fernando Gonzalez
Author-email: jfgonzalem@gmail.com
License: MIT
Keywords: LA CROSSE MOBILE TX60U-IT API Wrapper
Platform: UNKNOWN
Requires-Python: >=2.6, >3
